file_ext/__init__.py
logs/__init__.py
music_ext/__init__.py
Bitliker_libs-1.2.2.dist-info/LICENSE
Bitliker_libs-1.2.2.dist-info/METADATA
Bitliker_libs-1.2.2.dist-info/WHEEL
Bitliker_libs-1.2.2.dist-info/top_level.txt
Bitliker_libs-1.2.2.dist-info/RECORD
