Metadata-Version: 2.1
Name: Bitliker-libs
Version: 1.2.2
Summary: Bitliker 个人集合工具类
Home-page: https://github.com/BitlikerPython/Libs
Author: Bitliker
Author-email: gongpengming@163.com
License: MIT
Keywords: Bitliker Tools
Classifier: Development Status :: 3 - Alpha
Classifier: Intended Audience :: Developers
Classifier: License :: OSI Approved :: MIT License
Classifier: Programming Language :: Python :: 3
Classifier: Programming Language :: Python :: 3.10
Classifier: Programming Language :: Python :: 3.11
Classifier: Programming Language :: Python :: 3.12
Requires-Python: >=3.10
License-File: LICENSE
Requires-Dist: colorama
Requires-Dist: music-tag
Requires-Dist: requests
